README.rst
setup.py
palvin/__init__.py
palvin/main.py
palvin/mixin.py
palvin/model.py
palvin/query.py
palvin.egg-info/PKG-INFO
palvin.egg-info/SOURCES.txt
palvin.egg-info/dependency_links.txt
palvin.egg-info/requires.txt
palvin.egg-info/top_level.txt