Metadata-Version: 1.1
Name: palvin
Version: 0.0.2
Summary: Redice SQLAlchemy Boost Library. It's based sqlalchemy-wrapper
Home-page: https://github.com/redice-inc/palvin
Author: Redice
Author-email: devteam@redice-inc.com
License: MIT License
Platform: UNKNOWN
Classifier: Intended Audience :: Developers
Classifier: License :: OSI Approved :: MIT License
Classifier: Operating System :: OS Independent
Classifier: Programming Language :: Python :: 3
Classifier: Programming Language :: Python :: 3.2
Classifier: Programming Language :: Python :: 3.3
Classifier: Programming Language :: Python :: 3.4
Classifier: Programming Language :: Python :: 3.5
Classifier: Programming Language :: Python :: Implementation :: CPython
